[{"task":"makan","status":"[X]","createdAt":"2018-07-18T11:14:07.166Z","completedDate":"2018-07-18T11:14:36.461Z","tag":[["komik","novel"]]},{"task":"minum","status":"[ ]","createdAt":"2018-07-18T11:14:12.838Z","completedDate":"2018-07-18T11:14:12.838Z","tag":[["komik","novel"]]},{"task":"tidur","status":"[X]","createdAt":"2018-07-18T11:14:16.482Z","completedDate":"2018-07-18T11:14:40.982Z","tag":[["hobby","pet"]]},{"task":"lari","status":"[X]","createdAt":"2018-07-18T11:14:19.937Z","completedDate":"2018-07-18T11:14:44.281Z","tag":[]},{"task":"berenang","status":"[ ]","createdAt":"2018-07-18T11:14:24.320Z","completedDate":"2018-07-18T11:14:24.320Z","tag":[]}]